[
  {
    "id": 1,
    "name": "John doe",
    "timestamp": "14sep,2022",
    "imageUrl": "https://avatars.dicebear.com/api/avataaars/573cd8a3-c38e-4673-afd2-d9ac806ebabb.svg",
    "commentVotes": 80,
    "feedbacktitle": "Apple music UI revamp",
    "feedbackdetail": "We need to Make the UI more minimal and easy to naviigate",
    "category": "UI",
    "comments": [
      {
        "name": "Hali dae",
        "timestamp": "14sep,2022",
        "comment": "Hehehe"
      }
    ]
  },
  {
    "id": 2,
    "name": "Daisy milano",
    "timestamp": "15sep,2022",
    "imageUrl": "https://avatars.dicebear.com/api/avataaars/8e90bbeb-824e-45bb-ad90-c46ad78d874e.svg",
    "commentVotes": 73,
    "feedbacktitle": "ios 16 lockscreen update",
    "feedbackdetail": "ios 16 lockscreen needs a more customised outlook",
    "category": "Enhancement",
    "comments": [
      {
        "name": "Tim cook",
        "timestamp": "14 sep,2022",
        "comment": "i am calling out craig now"
      }
    ]
  },
  {
    "id": 3,
    "name": "Sun xuhan",
    "timestamp": "18sep,2022",
    "imageUrl": "https://api.dicebear.com/6.x/open-peeps/svg?seed=Chester",
    "commentVotes": 73,
    "feedbacktitle": "home screen icons are not displaying correct size",
    "feedbackdetail": "the new home screen icon size is not accurate with the design",
    "category": "Bug",
    "comments": [
      {
        "name": "Sam hill",
        "timestamp": "21 sep,2022",
        "comment": "Sent me a reproduction of the same!"
      }
    ]
  },
  {
    "id": 4,
    "name": "Grag rosky",
    "timestamp": "18sep,2022",
    "imageUrl": "https://api.dicebear.com/6.x/open-peeps/svg?seed=Chester",
    "commentVotes": 73,
    "feedbacktitle": "Adding apple watch support for new apps",
    "feedbackdetail": "we are planning to increase support for new apps in the apple watch store",
    "category": "Feature",
    "comments": [
      {
        "name": "Mike ross",
        "timestamp": "24 sep,2022",
        "comment": "working on it!"
      }
    ]
  },
  {
    "id": 5,
    "name": "Marry riches",
    "timestamp": "28sep,2022",
    "imageUrl": "https://api.dicebear.com/6.x/open-peeps/svg?seed=Boots",
    "commentVotes": 73,
    "feedbacktitle": "Adding support for ios 16 in iphone 7,iphone 8 and other lower iphone models",
    "feedbackdetail": "we are planning to increase support for older iphones",
    "category": "Feature",
    "comments": []
  }
]
